MANIFEST.in
README.rst
setup.py
docs/HISTORY.txt
docs/LICENSE.GPL
docs/LICENSE.txt
ftw/__init__.py
ftw.bridge.proxy.egg-info/PKG-INFO
ftw.bridge.proxy.egg-info/SOURCES.txt
ftw.bridge.proxy.egg-info/dependency_links.txt
ftw.bridge.proxy.egg-info/entry_points.txt
ftw.bridge.proxy.egg-info/namespace_packages.txt
ftw.bridge.proxy.egg-info/not-zip-safe
ftw.bridge.proxy.egg-info/requires.txt
ftw.bridge.proxy.egg-info/top_level.txt
ftw/bridge/__init__.py
ftw/bridge/proxy/__init__.py
ftw/bridge/proxy/authorization.py
ftw/bridge/proxy/client.py
ftw/bridge/proxy/configure.zcml
ftw/bridge/proxy/interfaces.py
ftw/bridge/proxy/proxy.py
ftw/bridge/proxy/testing.py
ftw/bridge/proxy/utils.py
ftw/bridge/proxy/views.py
ftw/bridge/proxy/templates/manage.pt
ftw/bridge/proxy/tests/__init__.py
ftw/bridge/proxy/tests/test_authorization.py
ftw/bridge/proxy/tests/test_client.py
ftw/bridge/proxy/tests/test_manage_view.py
ftw/bridge/proxy/tests/test_proxy.py
ftw/bridge/proxy/tests/test_proxy_view.py
ftw/bridge/proxy/tests/test_statuscheck_view.py
ftw/bridge/proxy/tests/test_utils.py