Metadata-Version: 1.0
Name: ftw.bridge.proxy
Version: 1.1.1
Summary: A pyramid based proxy application for proxying requests between plone instances.
Home-page: https://github.com/4teamwork/ftw.bridge.proxy
Author: Jonas Baumann
Author-email: mailto:info@4teamwork.ch
License: GPL2
Keywords: ftw bridge proxy requests
Platform: UNKNOWN
Classifier: Framework :: Pylons
Classifier: License :: OSI Approved :: GNU General Public License (GPL)
Classifier: Programming Language :: Python
